.gitignore
LICENSE
README.rst
setup.py
tox.ini
bin/merfi
merfi/__init__.py
merfi/base.py
merfi/collector.py
merfi/decorators.py
merfi/iso.py
merfi/logger.py
merfi/main.py
merfi/util.py
merfi.egg-info/PKG-INFO
merfi.egg-info/SOURCES.txt
merfi.egg-info/dependency_links.txt
merfi.egg-info/not-zip-safe
merfi.egg-info/pbr.json
merfi.egg-info/requires.txt
merfi.egg-info/top_level.txt
merfi/backends/__init__.py
merfi/backends/base.py
merfi/backends/gpg.py
merfi/backends/rpm_sign.py
merfi/tests/__init__.py
merfi/tests/conftest.py
merfi/tests/test_base.py
merfi/tests/test_iso.py
merfi/tests/test_main.py
merfi/tests/test_repocollector.py
merfi/tests/test_util.py
merfi/tests/util.py
merfi/tests/backends/__init__.py
merfi/tests/backends/test_gpg.py
merfi/tests/backends/test_rpm_sign.py
merfi/tests/fixtures/debrepos/jewel/dists/trusty/Release
merfi/tests/fixtures/debrepos/jewel/dists/xenial/Release
merfi/tests/fixtures/debrepos/jewel/pool/main/c/ceph/ceph.deb
merfi/tests/fixtures/debrepos/luminous/dists/trusty/Release
merfi/tests/fixtures/debrepos/luminous/dists/xenial/Release
merfi/tests/fixtures/debrepos/luminous/pool/main/c/ceph/ceph.deb