Metadata-Version: 1.1
Name: merfi
Version: 1.3.4
Summary: Signs release files
Home-page: http://github.com/alfredodeza/merfi
Author: Alfredo Deza
Author-email: alfredo@deza.pe
License: MIT
Keywords: rpm-sign,gpg,release,binaries
Platform: UNKNOWN
Classifier: Development Status :: 4 - Beta
Classifier: Intended Audience :: Developers
Classifier: License :: OSI Approved :: MIT License
Classifier: Topic :: Software Development :: Build Tools
Classifier: Topic :: Utilities
Classifier: Operating System :: MacOS :: MacOS X
Classifier: Operating System :: POSIX
Classifier: Programming Language :: Python :: 2.6
Classifier: Programming Language :: Python :: 2.7
Classifier: Programming Language :: Python :: 3.3
